{
  "last_updated": "2026-04-07 11:57:03",
  "total_count": 190,
  "success_count": 190,
  "realtime_count": 0,
  "funds": [
    {
      "code": "110020",
      "name": "易方达沪深300ETF联接A",
      "estimation": -0.29,
      "net_value": 1.7907,
      "est_value": 1.7855,
      "update_time": "2026-04-07 11:30",
      "data_source": "天天基金实时",
      "holdings": [],
      "success": true
    },
    {
      "code": "000961",
      "name": "天弘沪深300指数A",
      "estimation": -0.29,
      "net_value": 1.5747,
      "est_value": 1.5701,
      "update_time": "2026-04-07 11:30",
      "data_source": "天天基金实时",
      "holdings": [],
      "success": true
    },
    {
      "code": "110003",
      "name": "易方达上证50指数A",
      "estimation": 0.08,
      "net_value": 1.9928,
      "est_value": 1.9944,
      "update_time": "2026-04-07 11:30",
      "data_source": "天天基金实时",
      "holdings": [],
      "success": true
    },
    {
      "code": "001548",
      "name": "天弘上证50指数A",
      "estimation": 0.08,
      "net_value": 1.4231,
      "est_value": 1.4242,
      "update_time": "2026-04-07 11:30",
      "data_source": "天天基金实时",
      "holdings": [],
      "success": true
    },
    {
      "code": "160119",
      "name": "南方中证500ETF联接A",
      "estimation": 0.13,
      "net_value": 2.115,
      "est_value": 2.1177,
      "update_time": "2026-04-07 11:30",
      "data_source": "天天基金实时",
      "holdings": [],
      "success": true
    },
    {
      "code": "110026",
      "name": "易方达创业板ETF联接A",
      "estimation": -0.46,
      "net_value": 3.2182,
      "est_value": 3.2034,
      "update_time": "2026-04-07 11:30",
      "data_source": "天天基金实时",
      "holdings": [],
      "success": true
    },
    {
      "code": "003765",
      "name": "广发创业板ETF联接A",
      "estimation": -0.46,
      "net_value": 1.709,
      "est_value": 1.7011,
      "update_time": "2026-04-07 11:30",
      "data_source": "天天基金实时",
      "holdings": [],
      "success": true
    },
    {
      "code": "001632",
      "name": "天弘中证500指数A",
      "estimation": -0.06,
      "net_value": 1.9816,
      "est_value": 1.9804,
      "update_time": "2026-04-07 11:30",
      "data_source": "天天基金实时",
      "holdings": [],
      "success": true
    },
    {
      "code": "161017",
      "name": "富国中证500指数增强",
      "estimation": 0.13,
      "net_value": 2.519,
      "est_value": 2.5223,
      "update_time": "2026-04-07 11:30",
      "data_source": "天天基金实时",
      "holdings": [],
      "success": true
    },
    {
      "code": "005827",
      "name": "易方达蓝筹精选混合",
      "estimation": -0.17,
      "net_value": 1.7588,
      "est_value": 1.7559,
      "update_time": "2026-04-07 11:30",
      "data_source": "天天基金实时",
      "holdings": [],
      "success": true
    },
    {
      "code": "000478",
      "name": "建信中证500指数增强A",
      "estimation": 0.13,
      "net_value": 3.365,
      "est_value": 3.3694,
      "update_time": "2026-04-07 11:30",
      "data_source": "天天基金实时",
      "holdings": [],
      "success": true
    },
    {
      "code": "160706",
      "name": "嘉实沪深300ETF联接A",
      "estimation": -0.29,
      "net_value": 1.134,
      "est_value": 1.1307,
      "update_time": "2026-04-07 11:30",
      "data_source": "天天基金实时",
      "holdings": [],
      "success": true
    },
    {
      "code": "519671",
      "name": "银河沪深300价值指数A",
      "estimation": -0.37,
      "net_value": 1.979,
      "est_value": 1.9717,
      "update_time": "2026-04-07 11:30",
      "data_source": "天天基金实时",
      "holdings": [],
      "success": true
    },
    {
      "code": "000311",
      "name": "景顺长城沪深300指数增强",
      "estimation": -0.29,
      "net_value": 2.593,
      "est_value": 2.5855,
      "update_time": "2026-04-07 11:30",
      "data_source": "天天基金实时",
      "holdings": [],
      "success": true
    },
    {
      "code": "001015",
      "name": "华夏沪深300指数增强A",
      "estimation": -0.29,
      "net_value": 2.122,
      "est_value": 2.1158,
      "update_time": "2026-04-07 11:30",
      "data_source": "天天基金实时",
      "holdings": [],
      "success": true
    },
    {
      "code": "000051",
      "name": "华夏沪深300ETF联接A",
      "estimation": -0.29,
      "net_value": 1.6745,
      "est_value": 1.6696,
      "update_time": "2026-04-07 11:30",
      "data_source": "天天基金实时",
      "holdings": [],
      "success": true
    },
    {
      "code": "001550",
      "name": "天弘中证医药100指数A",
      "estimation": -0.28,
      "net_value": 0.7888,
      "est_value": 0.7866,
      "update_time": "2026-04-07 11:30",
      "data_source": "天天基金实时",
      "holdings": [],
      "success": true
    },
    {
      "code": "001594",
      "name": "天弘中证银行指数A",
      "estimation": -0.69,
      "net_value": 1.7397,
      "est_value": 1.7277,
      "update_time": "2026-04-07 11:30",
      "data_source": "天天基金实时",
      "holdings": [],
      "success": true
    },
    {
      "code": "001595",
      "name": "天弘中证证券保险指数A",
      "estimation": -0.69,
      "net_value": 1.6992,
      "est_value": 1.6875,
      "update_time": "2026-04-07 11:30",
      "data_source": "天天基金实时",
      "holdings": [],
      "success": true
    },
    {
      "code": "001631",
      "name": "天弘中证食品饮料指数A",
      "estimation": -0.06,
      "net_value": 2.0266,
      "est_value": 2.0254,
      "update_time": "2026-04-07 11:30",
      "data_source": "天天基金实时",
      "holdings": [],
      "success": true
    },
    {
      "code": "001617",
      "name": "天弘中证电子指数A",
      "estimation": 0.94,
      "net_value": 1.8417,
      "est_value": 1.859,
      "update_time": "2026-04-07 11:30",
      "data_source": "天天基金实时",
      "holdings": [],
      "success": true
    },
    {
      "code": "001618",
      "name": "天弘中证计算机指数A",
      "estimation": 0.94,
      "net_value": 1.799,
      "est_value": 1.8159,
      "update_time": "2026-04-07 11:30",
      "data_source": "天天基金实时",
      "holdings": [],
      "success": true
    },
    {
      "code": "001592",
      "name": "天弘中证证券指数A",
      "estimation": -0.46,
      "net_value": 1.2791,
      "est_value": 1.2732,
      "update_time": "2026-04-07 11:30",
      "data_source": "天天基金实时",
      "holdings": [],
      "success": true
    },
    {
      "code": "001616",
      "name": "天弘中证大宗商品指数A",
      "estimation": 0.01,
      "net_value": 3.077,
      "est_value": 3.0773,
      "update_time": "2026-04-07 11:30",
      "data_source": "天天基金实时",
      "holdings": [],
      "success": true
    },
    {
      "code": "005918",
      "name": "天弘中证科技100指数A",
      "estimation": -0.29,
      "net_value": 1.3782,
      "est_value": 1.3742,
      "update_time": "2026-04-07 11:30",
      "data_source": "天天基金实时",
      "holdings": [],
      "success": true
    },
    {
      "code": "110011",
      "name": "易方达中小盘混合",
      "estimation": -0.23,
      "net_value": 4.9108,
      "est_value": 4.8993,
      "update_time": "2026-04-07 11:30",
      "data_source": "天天基金实时",
      "holdings": [],
      "success": true
    },
    {
      "code": "006229",
      "name": "易方达成长精选混合A",
      "estimation": -0.47,
      "net_value": 1.4499,
      "est_value": 1.4431,
      "update_time": "2026-04-07 11:30",
      "data_source": "天天基金实时",
      "holdings": [],
      "success": true
    },
    {
      "code": "163406",
      "name": "兴全合润混合(LOF)",
      "estimation": -0.19,
      "net_value": 2.0818,
      "est_value": 2.0778,
      "update_time": "2026-04-07 11:30",
      "data_source": "天天基金实时",
      "holdings": [],
      "success": true
    },
    {
      "code": "163402",
      "name": "兴全趋势投资混合(LOF)",
      "estimation": 0.09,
      "net_value": 0.7533,
      "est_value": 0.754,
      "update_time": "2026-04-07 11:30",
      "data_source": "天天基金实时",
      "holdings": [],
      "success": true
    },
    {
      "code": "100032",
      "name": "富国中证红利指数增强A",
      "estimation": 0.09,
      "net_value": 0.979,
      "est_value": 0.9799,
      "update_time": "2026-04-07 11:30",
      "data_source": "天天基金实时",
      "holdings": [],
      "success": true
    },
    {
      "code": "161033",
      "name": "富国中证智能汽车指数(LOF)A",
      "estimation": -0.38,
      "net_value": 1.874,
      "est_value": 1.8669,
      "update_time": "2026-04-07 11:30",
      "data_source": "天天基金实时",
      "holdings": [],
      "success": true
    },
    {
      "code": "161028",
      "name": "富国中证新能源汽车指数(LOF)A",
      "estimation": -0.53,
      "net_value": 1.131,
      "est_value": 1.125,
      "update_time": "2026-04-07 11:30",
      "data_source": "天天基金实时",
      "holdings": [],
      "success": true
    },
    {
      "code": "001156",
      "name": "申万菱信新能源汽车主题混合",
      "estimation": -0.55,
      "net_value": 2.681,
      "est_value": 2.6663,
      "update_time": "2026-04-07 11:30",
      "data_source": "天天基金实时",
      "holdings": [],
      "success": true
    },
    {
      "code": "001410",
      "name": "信达澳银新能源产业股票",
      "estimation": 0.58,
      "net_value": 5.087,
      "est_value": 5.1163,
      "update_time": "2026-04-07 11:30",
      "data_source": "天天基金实时",
      "holdings": [],
      "success": true
    },
    {
      "code": "001475",
      "name": "易方达国防军工混合",
      "estimation": -0.41,
      "net_value": 1.811,
      "est_value": 1.8036,
      "update_time": "2026-04-07 11:30",
      "data_source": "天天基金实时",
      "holdings": [],
      "success": true
    },
    {
      "code": "003834",
      "name": "华夏能源革新股票A",
      "estimation": -1.03,
      "net_value": 3.359,
      "est_value": 3.3245,
      "update_time": "2026-04-07 11:30",
      "data_source": "天天基金实时",
      "holdings": [],
      "success": true
    },
    {
      "code": "161024",
      "name": "富国中证军工指数(LOF)A",
      "estimation": -0.32,
      "net_value": 1.234,
      "est_value": 1.23,
      "update_time": "2026-04-07 11:30",
      "data_source": "天天基金实时",
      "holdings": [],
      "success": true
    },
    {
      "code": "501057",
      "name": "汇添富中证新能源汽车产业指数(LOF)A",
      "estimation": -0.54,
      "net_value": 2.3973,
      "est_value": 2.3844,
      "update_time": "2026-04-07 11:30",
      "data_source": "天天基金实时",
      "holdings": [],
      "success": true
    },
    {
      "code": "160225",
      "name": "国泰国证新能源汽车指数(LOF)",
      "estimation": -0.52,
      "net_value": 1.9038,
      "est_value": 1.8939,
      "update_time": "2026-04-07 11:30",
      "data_source": "天天基金实时",
      "holdings": [],
      "success": true
    },
    {
      "code": "012733",
      "name": "富国中证芯片产业指数(LOF)A",
      "estimation": 0.49,
      "net_value": 1.6764,
      "est_value": 1.6846,
      "update_time": "2026-04-07 11:30",
      "data_source": "天天基金实时",
      "holdings": [],
      "success": true
    },
    {
      "code": "008888",
      "name": "华夏国证半导体芯片ETF联接A",
      "estimation": 1.86,
      "net_value": 1.3993,
      "est_value": 1.4253,
      "update_time": "2026-04-07 11:30",
      "data_source": "天天基金实时",
      "holdings": [],
      "success": true
    },
    {
      "code": "007300",
      "name": "国联安中证全指半导体ETF联接A",
      "estimation": 1.94,
      "net_value": 2.7792,
      "est_value": 2.8331,
      "update_time": "2026-04-07 11:30",
      "data_source": "天天基金实时",
      "holdings": [],
      "success": true
    },
    {
      "code": "515030",
      "name": "华夏中证新能源汽车ETF",
      "estimation": -0.53,
      "net_value": 1.7929,
      "est_value": 1.7834,
      "update_time": "2026-04-07 11:30",
      "data_source": "天天基金实时",
      "holdings": [],
      "success": true
    },
    {
      "code": "515000",
      "name": "华夏中证5G通信主题ETF",
      "estimation": -0.12,
      "net_value": 0.9667,
      "est_value": 0.9655,
      "update_time": "2026-04-07 11:30",
      "data_source": "天天基金实时",
      "holdings": [],
      "success": true
    },
    {
      "code": "516160",
      "name": "南方中证新能源ETF",
      "estimation": -0.27,
      "net_value": 2.857,
      "est_value": 2.8493,
      "update_time": "2026-04-07 11:30",
      "data_source": "天天基金实时",
      "holdings": [],
      "success": true
    },
    {
      "code": "012850",
      "name": "易方达中证人工智能主题ETF联接A",
      "estimation": -0.17,
      "net_value": 1.109,
      "est_value": 1.1072,
      "update_time": "2026-04-07 11:30",
      "data_source": "天天基金实时",
      "holdings": [],
      "success": true
    },
    {
      "code": "001643",
      "name": "汇丰晋信智造先锋股票A",
      "estimation": -0.1,
      "net_value": 2.5506,
      "est_value": 2.548,
      "update_time": "2026-04-07 11:30",
      "data_source": "天天基金实时",
      "holdings": [],
      "success": true
    },
    {
      "code": "003956",
      "name": "南方教育股票",
      "estimation": -0.04,
      "net_value": 2.1354,
      "est_value": 2.1346,
      "update_time": "2026-04-07 11:30",
      "data_source": "天天基金实时",
      "holdings": [],
      "success": true
    },
    {
      "code": "004854",
      "name": "广发中证全指汽车指数A",
      "estimation": -0.31,
      "net_value": 1.6599,
      "est_value": 1.6548,
      "update_time": "2026-04-07 11:30",
      "data_source": "天天基金实时",
      "holdings": [],
      "success": true
    },
    {
      "code": "005689",
      "name": "中欧科创主题3年封闭运作灵活配置混合",
      "estimation": -1.03,
      "net_value": 2.8912,
      "est_value": 2.8614,
      "update_time": "2026-04-07 11:30",
      "data_source": "天天基金实时",
      "holdings": [],
      "success": true
    },
    {
      "code": "006098",
      "name": "华宝券商ETF联接A",
      "estimation": -0.23,
      "net_value": 1.4294,
      "est_value": 1.4261,
      "update_time": "2026-04-07 11:30",
      "data_source": "天天基金实时",
      "holdings": [],
      "success": true
    },
    {
      "code": "008281",
      "name": "华夏中证新能源汽车ETF联接A",
      "estimation": 1.81,
      "net_value": 1.7993,
      "est_value": 1.8319,
      "update_time": "2026-04-07 11:30",
      "data_source": "天天基金实时",
      "holdings": [],
      "success": true
    },
    {
      "code": "009644",
      "name": "易方达中证海外中国互联网50ETF联接A",
      "estimation": -0.59,
      "net_value": 2.1757,
      "est_value": 2.163,
      "update_time": "2026-04-07 11:30",
      "data_source": "天天基金实时",
      "holdings": [],
      "success": true
    },
    {
      "code": "010014",
      "name": "易方达中证人工智能主题ETF联接C",
      "estimation": -0.08,
      "net_value": 1.2085,
      "est_value": 1.2076,
      "update_time": "2026-04-07 11:30",
      "data_source": "天天基金实时",
      "holdings": [],
      "success": true
    },
    {
      "code": "011103",
      "name": "汇添富中证新能源汽车产业指数(LOF)C",
      "estimation": -0.08,
      "net_value": 0.8314,
      "est_value": 0.8307,
      "update_time": "2026-04-07 11:30",
      "data_source": "天天基金实时",
      "holdings": [],
      "success": true
    },
    {
      "code": "012348",
      "name": "华夏中证动漫游戏ETF联接A",
      "estimation": -1.54,
      "net_value": 0.6481,
      "est_value": 0.6381,
      "update_time": "2026-04-02 16:00",
      "data_source": "天天基金实时",
      "holdings": [],
      "success": true
    },
    {
      "code": "013402",
      "name": "华夏中证云计算与大数据主题ETF联接A",
      "estimation": -1.54,
      "net_value": 0.786,
      "est_value": 0.7739,
      "update_time": "2026-04-02 16:00",
      "data_source": "天天基金实时",
      "holdings": [],
      "success": true
    },
    {
      "code": "159995",
      "name": "华夏国证半导体芯片ETF",
      "estimation": 1.86,
      "net_value": 1.6174,
      "est_value": 1.6475,
      "update_time": "2026-04-07 11:30",
      "data_source": "天天基金实时",
      "holdings": [],
      "success": true
    },
    {
      "code": "515790",
      "name": "华夏中证动漫游戏ETF",
      "estimation": -0.08,
      "net_value": 0.9832,
      "est_value": 0.9824,
      "update_time": "2026-04-07 11:30",
      "data_source": "天天基金实时",
      "holdings": [],
      "success": true
    },
    {
      "code": "516110",
      "name": "华夏中证人工智能主题ETF",
      "estimation": -1.06,
      "net_value": 1.28,
      "est_value": 1.2664,
      "update_time": "2026-04-07 11:30",
      "data_source": "天天基金实时",
      "holdings": [],
      "success": true
    },
    {
      "code": "516510",
      "name": "华夏中证云计算与大数据主题ETF",
      "estimation": -0.49,
      "net_value": 1.6181,
      "est_value": 1.6102,
      "update_time": "2026-04-07 11:30",
      "data_source": "天天基金实时",
      "holdings": [],
      "success": true
    },
    {
      "code": "159806",
      "name": "国泰中证全指通信设备ETF",
      "estimation": -0.53,
      "net_value": 0.7824,
      "est_value": 0.7783,
      "update_time": "2026-04-07 11:30",
      "data_source": "天天基金实时",
      "holdings": [],
      "success": true
    },
    {
      "code": "159928",
      "name": "汇添富中证主要消费ETF",
      "estimation": 0.22,
      "net_value": 0.7467,
      "est_value": 0.7483,
      "update_time": "2026-04-07 11:30",
      "data_source": "天天基金实时",
      "holdings": [],
      "success": true
    },
    {
      "code": "512480",
      "name": "国联安中证全指半导体产品与设备ETF",
      "estimation": 1.94,
      "net_value": 1.4124,
      "est_value": 1.4398,
      "update_time": "2026-04-07 11:30",
      "data_source": "天天基金实时",
      "holdings": [],
      "success": true
    },
    {
      "code": "512760",
      "name": "国泰中证全指通信设备ETF",
      "estimation": 1.81,
      "net_value": 0.7665,
      "est_value": 0.7804,
      "update_time": "2026-04-07 11:30",
      "data_source": "天天基金实时",
      "holdings": [],
      "success": true
    },
    {
      "code": "159881",
      "name": "易方达中证新能源ETF",
      "estimation": 0.07,
      "net_value": 1.9043,
      "est_value": 1.9056,
      "update_time": "2026-04-07 11:30",
      "data_source": "天天基金实时",
      "holdings": [],
      "success": true
    },
    {
      "code": "512170",
      "name": "华宝中证医疗ETF",
      "estimation": 0.23,
      "net_value": 0.3309,
      "est_value": 0.3317,
      "update_time": "2026-04-07 11:30",
      "data_source": "天天基金实时",
      "holdings": [],
      "success": true
    },
    {
      "code": "512690",
      "name": "鹏华中证酒ETF",
      "estimation": -0.37,
      "net_value": 0.4932,
      "est_value": 0.4914,
      "update_time": "2026-04-07 11:30",
      "data_source": "天天基金实时",
      "holdings": [],
      "success": true
    },
    {
      "code": "512660",
      "name": "国泰中证军工ETF",
      "estimation": -0.31,
      "net_value": 1.2679,
      "est_value": 1.264,
      "update_time": "2026-04-07 11:30",
      "data_source": "天天基金实时",
      "holdings": [],
      "success": true
    },
    {
      "code": "512980",
      "name": "广发中证传媒ETF",
      "estimation": 0.56,
      "net_value": 0.9527,
      "est_value": 0.958,
      "update_time": "2026-04-07 11:30",
      "data_source": "天天基金实时",
      "holdings": [],
      "success": true
    },
    {
      "code": "161726",
      "name": "招商国证生物医药指数(LOF)A",
      "estimation": -0.45,
      "net_value": 0.4,
      "est_value": 0.3982,
      "update_time": "2026-04-07 11:30",
      "data_source": "天天基金实时",
      "holdings": [],
      "success": true
    },
    {
      "code": "003096",
      "name": "中欧医疗健康混合A",
      "estimation": -0.44,
      "net_value": 1.7577,
      "est_value": 1.7499,
      "update_time": "2026-04-07 11:30",
      "data_source": "天天基金实时",
      "holdings": [],
      "success": true
    },
    {
      "code": "110023",
      "name": "易方达医疗保健行业混合",
      "estimation": -0.75,
      "net_value": 4.118,
      "est_value": 4.0871,
      "update_time": "2026-04-07 11:30",
      "data_source": "天天基金实时",
      "holdings": [],
      "success": true
    },
    {
      "code": "000220",
      "name": "富国医疗保健行业混合A",
      "estimation": -0.48,
      "net_value": 3.167,
      "est_value": 3.1517,
      "update_time": "2026-04-07 11:30",
      "data_source": "天天基金实时",
      "holdings": [],
      "success": true
    },
    {
      "code": "001898",
      "name": "易方达大健康主题混合",
      "estimation": 0.1,
      "net_value": 2.337,
      "est_value": 2.3394,
      "update_time": "2026-04-07 11:30",
      "data_source": "天天基金实时",
      "holdings": [],
      "success": true
    },
    {
      "code": "005112",
      "name": "银华中证创新药产业ETF联接A",
      "estimation": -0.11,
      "net_value": 1.3545,
      "est_value": 1.353,
      "update_time": "2026-04-07 11:30",
      "data_source": "天天基金实时",
      "holdings": [],
      "success": true
    },
    {
      "code": "009396",
      "name": "汇添富中证生物科技指数(LOF)A",
      "estimation": 0.02,
      "net_value": 1.0136,
      "est_value": 1.0138,
      "update_time": "2026-04-07 11:30",
      "data_source": "天天基金实时",
      "holdings": [],
      "success": true
    },
    {
      "code": "001717",
      "name": "工银瑞信前沿医疗股票A",
      "estimation": -1.1,
      "net_value": 3.226,
      "est_value": 3.1907,
      "update_time": "2026-04-07 11:30",
      "data_source": "天天基金实时",
      "holdings": [],
      "success": true
    },
    {
      "code": "006002",
      "name": "工银瑞信医药健康行业股票A",
      "estimation": -0.25,
      "net_value": 2.3302,
      "est_value": 2.3245,
      "update_time": "2026-04-07 11:30",
      "data_source": "天天基金实时",
      "holdings": [],
      "success": true
    },
    {
      "code": "001645",
      "name": "国泰大健康股票A",
      "estimation": 0.48,
      "net_value": 2.131,
      "est_value": 2.1413,
      "update_time": "2026-04-07 11:30",
      "data_source": "天天基金实时",
      "holdings": [],
      "success": true
    },
    {
      "code": "001915",
      "name": "宝盈医疗健康沪港深股票A",
      "estimation": -0.74,
      "net_value": 2.114,
      "est_value": 2.0984,
      "update_time": "2026-04-07 11:30",
      "data_source": "天天基金实时",
      "holdings": [],
      "success": true
    },
    {
      "code": "005303",
      "name": "嘉实医药健康股票A",
      "estimation": -0.27,
      "net_value": 1.7922,
      "est_value": 1.7873,
      "update_time": "2026-04-07 11:30",
      "data_source": "天天基金实时",
      "holdings": [],
      "success": true
    },
    {
      "code": "001766",
      "name": "上投摩根医疗健康股票A",
      "estimation": -0.49,
      "net_value": 1.5718,
      "est_value": 1.5641,
      "update_time": "2026-04-07 11:30",
      "data_source": "天天基金实时",
      "holdings": [],
      "success": true
    },
    {
      "code": "004905",
      "name": "华安安康灵活配置混合A",
      "estimation": -0.89,
      "net_value": 2.7953,
      "est_value": 2.7705,
      "update_time": "2026-04-07 11:30",
      "data_source": "天天基金实时",
      "holdings": [],
      "success": true
    },
    {
      "code": "005237",
      "name": "银华医疗健康量化股票发起式A",
      "estimation": -0.48,
      "net_value": 1.216,
      "est_value": 1.2102,
      "update_time": "2026-04-07 11:30",
      "data_source": "天天基金实时",
      "holdings": [],
      "success": true
    },
    {
      "code": "001551",
      "name": "天弘中证医药100指数C",
      "estimation": -0.28,
      "net_value": 0.771,
      "est_value": 0.7688,
      "update_time": "2026-04-07 11:30",
      "data_source": "天天基金实时",
      "holdings": [],
      "success": true
    },
    {
      "code": "003095",
      "name": "中欧医疗健康混合C",
      "estimation": -0.44,
      "net_value": 1.8463,
      "est_value": 1.8381,
      "update_time": "2026-04-07 11:30",
      "data_source": "天天基金实时",
      "holdings": [],
      "success": true
    },
    {
      "code": "004075",
      "name": "交银施罗德医药创新股票",
      "estimation": -0.59,
      "net_value": 2.5091,
      "est_value": 2.4942,
      "update_time": "2026-04-07 11:30",
      "data_source": "天天基金实时",
      "holdings": [],
      "success": true
    },
    {
      "code": "007255",
      "name": "国泰中证生物医药ETF联接A",
      "estimation": 0.09,
      "net_value": 1.3584,
      "est_value": 1.3596,
      "update_time": "2026-04-07 11:30",
      "data_source": "天天基金实时",
      "holdings": [],
      "success": true
    },
    {
      "code": "008278",
      "name": "华宝中证医疗ETF联接A",
      "estimation": 0.04,
      "net_value": 1.202,
      "est_value": 1.2025,
      "update_time": "2026-04-07 11:30",
      "data_source": "天天基金实时",
      "holdings": [],
      "success": true
    },
    {
      "code": "010387",
      "name": "易方达医药生物股票A",
      "estimation": -0.69,
      "net_value": 0.8675,
      "est_value": 0.8615,
      "update_time": "2026-04-07 11:30",
      "data_source": "天天基金实时",
      "holdings": [],
      "success": true
    },
    {
      "code": "011121",
      "name": "汇添富中证生物科技指数(LOF)C",
      "estimation": -0.19,
      "net_value": 0.4789,
      "est_value": 0.478,
      "update_time": "2026-04-07 11:30",
      "data_source": "天天基金实时",
      "holdings": [],
      "success": true
    },
    {
      "code": "012328",
      "name": "华夏中证创新药产业ETF联接A",
      "estimation": -0.27,
      "net_value": 0.7357,
      "est_value": 0.7337,
      "update_time": "2026-04-07 11:30",
      "data_source": "天天基金实时",
      "holdings": [],
      "success": true
    },
    {
      "code": "159938",
      "name": "广发中证全指医药卫生ETF",
      "estimation": -0.11,
      "net_value": 0.6454,
      "est_value": 0.6447,
      "update_time": "2026-04-07 11:30",
      "data_source": "天天基金实时",
      "holdings": [],
      "success": true
    },
    {
      "code": "512010",
      "name": "易方达沪深300医药卫生ETF",
      "estimation": -0.03,
      "net_value": 0.3681,
      "est_value": 0.368,
      "update_time": "2026-04-07 11:30",
      "data_source": "天天基金实时",
      "holdings": [],
      "success": true
    },
    {
      "code": "512120",
      "name": "华安中证细分医药ETF",
      "estimation": -0.25,
      "net_value": 0.4588,
      "est_value": 0.4576,
      "update_time": "2026-04-07 11:30",
      "data_source": "天天基金实时",
      "holdings": [],
      "success": true
    },
    {
      "code": "512290",
      "name": "国泰中证生物医药ETF",
      "estimation": -0.42,
      "net_value": 0.9716,
      "est_value": 0.9675,
      "update_time": "2026-04-07 11:30",
      "data_source": "天天基金实时",
      "holdings": [],
      "success": true
    },
    {
      "code": "512610",
      "name": "嘉实中证医药卫生ETF",
      "estimation": 0.0,
      "net_value": null,
      "est_value": null,
      "update_time": "无数据",
      "data_source": "无",
      "holdings": [],
      "success": true
    },
    {
      "code": "159929",
      "name": "汇添富中证医药卫生ETF",
      "estimation": -0.12,
      "net_value": 1.3298,
      "est_value": 1.3282,
      "update_time": "2026-04-07 11:30",
      "data_source": "天天基金实时",
      "holdings": [],
      "success": true
    },
    {
      "code": "002190",
      "name": "农银汇理医疗保健股票",
      "estimation": -0.45,
      "net_value": 2.9582,
      "est_value": 2.9449,
      "update_time": "2026-04-07 11:30",
      "data_source": "天天基金实时",
      "holdings": [],
      "success": true
    },
    {
      "code": "161725",
      "name": "招商中证白酒指数(LOF)A",
      "estimation": -0.59,
      "net_value": 0.6393,
      "est_value": 0.6355,
      "update_time": "2026-04-07 11:30",
      "data_source": "天天基金实时",
      "holdings": [],
      "success": true
    },
    {
      "code": "160632",
      "name": "鹏华酒指数(LOF)A",
      "estimation": -0.37,
      "net_value": 0.3076,
      "est_value": 0.3065,
      "update_time": "2026-04-07 11:30",
      "data_source": "天天基金实时",
      "holdings": [],
      "success": true
    },
    {
      "code": "000248",
      "name": "汇添富中证主要消费ETF联接A",
      "estimation": 0.22,
      "net_value": 2.0395,
      "est_value": 2.044,
      "update_time": "2026-04-07 11:30",
      "data_source": "天天基金实时",
      "holdings": [],
      "success": true
    },
    {
      "code": "160222",
      "name": "国泰国证食品饮料行业指数",
      "estimation": -0.27,
      "net_value": 0.7335,
      "est_value": 0.7315,
      "update_time": "2026-04-07 11:30",
      "data_source": "天天基金实时",
      "holdings": [],
      "success": true
    },
    {
      "code": "005235",
      "name": "银华食品饮料量化股票发起式A",
      "estimation": -0.18,
      "net_value": 1.5936,
      "est_value": 1.5907,
      "update_time": "2026-04-07 11:30",
      "data_source": "天天基金实时",
      "holdings": [],
      "success": true
    },
    {
      "code": "001679",
      "name": "前海开源中国稀缺资产混合A",
      "estimation": -0.36,
      "net_value": 1.743,
      "est_value": 1.7366,
      "update_time": "2026-04-07 11:30",
      "data_source": "天天基金实时",
      "holdings": [],
      "success": true
    },
    {
      "code": "000083",
      "name": "汇添富消费行业混合",
      "estimation": -0.87,
      "net_value": 4.636,
      "est_value": 4.5955,
      "update_time": "2026-04-07 11:30",
      "data_source": "天天基金实时",
      "holdings": [],
      "success": true
    },
    {
      "code": "001726",
      "name": "汇添富新兴消费股票A",
      "estimation": -0.67,
      "net_value": 1.348,
      "est_value": 1.3389,
      "update_time": "2026-04-07 11:30",
      "data_source": "天天基金实时",
      "holdings": [],
      "success": true
    },
    {
      "code": "001644",
      "name": "国泰大农业股票A",
      "estimation": -0.1,
      "net_value": 2.4225,
      "est_value": 2.42,
      "update_time": "2026-04-07 11:30",
      "data_source": "天天基金实时",
      "holdings": [],
      "success": true
    },
    {
      "code": "002560",
      "name": "诺安和鑫灵活配置混合",
      "estimation": 0.71,
      "net_value": 2.2201,
      "est_value": 2.2358,
      "update_time": "2026-04-07 11:30",
      "data_source": "天天基金实时",
      "holdings": [],
      "success": true
    },
    {
      "code": "001102",
      "name": "前海开源国家比较优势混合",
      "estimation": -0.36,
      "net_value": 2.168,
      "est_value": 2.1601,
      "update_time": "2026-04-07 11:30",
      "data_source": "天天基金实时",
      "holdings": [],
      "success": true
    },
    {
      "code": "002621",
      "name": "中欧消费主题股票A",
      "estimation": 0.08,
      "net_value": 1.3415,
      "est_value": 1.3425,
      "update_time": "2026-04-07 11:30",
      "data_source": "天天基金实时",
      "holdings": [],
      "success": true
    },
    {
      "code": "004851",
      "name": "广发医疗保健股票A",
      "estimation": -0.68,
      "net_value": 1.9251,
      "est_value": 1.9121,
      "update_time": "2026-04-07 11:30",
      "data_source": "天天基金实时",
      "holdings": [],
      "success": true
    },
    {
      "code": "007119",
      "name": "广发科技先锋混合A",
      "estimation": -0.37,
      "net_value": 1.9545,
      "est_value": 1.9472,
      "update_time": "2026-04-07 11:30",
      "data_source": "天天基金实时",
      "holdings": [],
      "success": true
    },
    {
      "code": "008087",
      "name": "华夏中证内地低碳经济主题ETF联接A",
      "estimation": -0.86,
      "net_value": 2.237,
      "est_value": 2.2178,
      "update_time": "2026-04-07 11:30",
      "data_source": "天天基金实时",
      "holdings": [],
      "success": true
    },
    {
      "code": "009265",
      "name": "南方优享分红灵活配置混合A",
      "estimation": -0.26,
      "net_value": 0.8098,
      "est_value": 0.8077,
      "update_time": "2026-04-07 11:30",
      "data_source": "天天基金实时",
      "holdings": [],
      "success": true
    },
    {
      "code": "159736",
      "name": "嘉实中证稀土产业ETF",
      "estimation": -0.06,
      "net_value": 0.6436,
      "est_value": 0.6432,
      "update_time": "2026-04-07 11:30",
      "data_source": "天天基金实时",
      "holdings": [],
      "success": true
    },
    {
      "code": "512200",
      "name": "南方中证全指房地产ETF",
      "estimation": 0.01,
      "net_value": 1.2992,
      "est_value": 1.2993,
      "update_time": "2026-04-07 11:30",
      "data_source": "天天基金实时",
      "holdings": [],
      "success": true
    },
    {
      "code": "512600",
      "name": "嘉实中证主要消费ETF",
      "estimation": 0.22,
      "net_value": 0.6364,
      "est_value": 0.6378,
      "update_time": "2026-04-07 11:30",
      "data_source": "天天基金实时",
      "holdings": [],
      "success": true
    },
    {
      "code": "512800",
      "name": "华宝中证银行ETF",
      "estimation": -0.69,
      "net_value": 0.7964,
      "est_value": 0.7909,
      "update_time": "2026-04-07 11:30",
      "data_source": "天天基金实时",
      "holdings": [],
      "success": true
    },
    {
      "code": "513050",
      "name": "易方达中概互联50ETF",
      "estimation": 0.0,
      "net_value": null,
      "est_value": null,
      "update_time": "无数据",
      "data_source": "无",
      "holdings": [],
      "success": true
    },
    {
      "code": "515220",
      "name": "国泰中证煤炭ETF",
      "estimation": 1.5,
      "net_value": 1.1929,
      "est_value": 1.2108,
      "update_time": "2026-04-07 11:30",
      "data_source": "天天基金实时",
      "holdings": [],
      "success": true
    },
    {
      "code": "516970",
      "name": "广发中证基建工程ETF",
      "estimation": 0.38,
      "net_value": 1.1787,
      "est_value": 1.1832,
      "update_time": "2026-04-07 11:30",
      "data_source": "天天基金实时",
      "holdings": [],
      "success": true
    },
    {
      "code": "159825",
      "name": "德邦中证沪港深高股息ETF",
      "estimation": 1.93,
      "net_value": 0.8229,
      "est_value": 0.8388,
      "update_time": "2026-04-07 11:30",
      "data_source": "天天基金实时",
      "holdings": [],
      "success": true
    },
    {
      "code": "159869",
      "name": "华泰柏瑞中证红利低波动ETF",
      "estimation": -0.27,
      "net_value": 1.2749,
      "est_value": 1.2715,
      "update_time": "2026-04-07 11:30",
      "data_source": "天天基金实时",
      "holdings": [],
      "success": true
    },
    {
      "code": "515180",
      "name": "华夏中证全指房地产ETF",
      "estimation": 0.09,
      "net_value": 1.4089,
      "est_value": 1.4102,
      "update_time": "2026-04-07 11:30",
      "data_source": "天天基金实时",
      "holdings": [],
      "success": true
    },
    {
      "code": "515650",
      "name": "富国中证消费50ETF",
      "estimation": -0.27,
      "net_value": 1.1131,
      "est_value": 1.1101,
      "update_time": "2026-04-07 11:30",
      "data_source": "天天基金实时",
      "holdings": [],
      "success": true
    },
    {
      "code": "516670",
      "name": "招商中证白酒ETF",
      "estimation": 2.41,
      "net_value": 0.6693,
      "est_value": 0.6854,
      "update_time": "2026-04-07 11:30",
      "data_source": "天天基金实时",
      "holdings": [],
      "success": true
    },
    {
      "code": "512580",
      "name": "广发中证环保产业ETF",
      "estimation": -0.45,
      "net_value": 1.2737,
      "est_value": 1.268,
      "update_time": "2026-04-07 11:30",
      "data_source": "天天基金实时",
      "holdings": [],
      "success": true
    },
    {
      "code": "161121",
      "name": "易方达银行指数(LOF)A",
      "estimation": -0.69,
      "net_value": 1.5922,
      "est_value": 1.5812,
      "update_time": "2026-04-07 11:30",
      "data_source": "天天基金实时",
      "holdings": [],
      "success": true
    },
    {
      "code": "160628",
      "name": "鹏华地产指数(LOF)A",
      "estimation": -0.59,
      "net_value": 0.5214,
      "est_value": 0.5183,
      "update_time": "2026-04-07 11:30",
      "data_source": "天天基金实时",
      "holdings": [],
      "success": true
    },
    {
      "code": "160625",
      "name": "鹏华证券保险指数(LOF)A",
      "estimation": -0.58,
      "net_value": 0.8104,
      "est_value": 0.8057,
      "update_time": "2026-04-07 11:30",
      "data_source": "天天基金实时",
      "holdings": [],
      "success": true
    },
    {
      "code": "512000",
      "name": "华宝中证全指证券公司ETF",
      "estimation": -0.23,
      "net_value": 0.486,
      "est_value": 0.4849,
      "update_time": "2026-04-07 11:30",
      "data_source": "天天基金实时",
      "holdings": [],
      "success": true
    },
    {
      "code": "160218",
      "name": "国泰国证房地产行业指数",
      "estimation": 0.11,
      "net_value": 0.6039,
      "est_value": 0.6046,
      "update_time": "2026-04-07 11:30",
      "data_source": "天天基金实时",
      "holdings": [],
      "success": true
    },
    {
      "code": "501029",
      "name": "华宝标普中国A股红利机会指数(LOF)A",
      "estimation": 0.0,
      "net_value": null,
      "est_value": null,
      "update_time": "无数据",
      "data_source": "无",
      "holdings": [],
      "success": true
    },
    {
      "code": "007531",
      "name": "易方达中证银行ETF联接A",
      "estimation": -0.24,
      "net_value": 1.3914,
      "est_value": 1.388,
      "update_time": "2026-04-07 11:30",
      "data_source": "天天基金实时",
      "holdings": [],
      "success": true
    },
    {
      "code": "008279",
      "name": "华宝中证银行ETF联接A",
      "estimation": 1.49,
      "net_value": 2.2176,
      "est_value": 2.2507,
      "update_time": "2026-04-07 11:30",
      "data_source": "天天基金实时",
      "holdings": [],
      "success": true
    },
    {
      "code": "009612",
      "name": "华宝中证全指证券公司ETF联接A",
      "estimation": 0.47,
      "net_value": 1.1885,
      "est_value": 1.1941,
      "update_time": "2026-04-07 11:30",
      "data_source": "天天基金实时",
      "holdings": [],
      "success": true
    },
    {
      "code": "512070",
      "name": "易方达沪深300非银ETF",
      "estimation": -0.62,
      "net_value": 0.7712,
      "est_value": 0.7664,
      "update_time": "2026-04-07 11:30",
      "data_source": "天天基金实时",
      "holdings": [],
      "success": true
    },
    {
      "code": "512640",
      "name": "嘉实中证金融地产ETF",
      "estimation": -0.59,
      "net_value": 2.2902,
      "est_value": 2.2767,
      "update_time": "2026-04-07 11:30",
      "data_source": "天天基金实时",
      "holdings": [],
      "success": true
    },
    {
      "code": "515560",
      "name": "易方达中证银行ETF",
      "estimation": -0.23,
      "net_value": 0.9327,
      "est_value": 0.9305,
      "update_time": "2026-04-07 11:30",
      "data_source": "天天基金实时",
      "holdings": [],
      "success": true
    },
    {
      "code": "515900",
      "name": "华夏中证全指证券公司ETF",
      "estimation": -0.06,
      "net_value": 1.6592,
      "est_value": 1.6582,
      "update_time": "2026-04-07 11:30",
      "data_source": "天天基金实时",
      "holdings": [],
      "success": true
    },
    {
      "code": "159940",
      "name": "广发中证全指金融地产ETF",
      "estimation": -0.57,
      "net_value": 1.1735,
      "est_value": 1.1668,
      "update_time": "2026-04-07 11:30",
      "data_source": "天天基金实时",
      "holdings": [],
      "success": true
    },
    {
      "code": "512400",
      "name": "南方中证申万有色金属ETF",
      "estimation": 0.14,
      "net_value": 1.9721,
      "est_value": 1.9749,
      "update_time": "2026-04-07 11:30",
      "data_source": "天天基金实时",
      "holdings": [],
      "success": true
    },
    {
      "code": "510230",
      "name": "国泰上证180金融ETF",
      "estimation": -0.77,
      "net_value": 1.285,
      "est_value": 1.2752,
      "update_time": "2026-04-07 11:30",
      "data_source": "天天基金实时",
      "holdings": [],
      "success": true
    },
    {
      "code": "160620",
      "name": "鹏华中证A股资源产业指数(LOF)",
      "estimation": 0.45,
      "net_value": 2.9284,
      "est_value": 2.9416,
      "update_time": "2026-04-07 11:30",
      "data_source": "天天基金实时",
      "holdings": [],
      "success": true
    },
    {
      "code": "161819",
      "name": "银华中证内地资源指数(LOF)",
      "estimation": 0.0,
      "net_value": null,
      "est_value": null,
      "update_time": "无数据",
      "data_source": "无",
      "holdings": [],
      "success": true
    },
    {
      "code": "160216",
      "name": "国泰大宗商品配置(LOF)",
      "estimation": 0.0,
      "net_value": null,
      "est_value": null,
      "update_time": "无数据",
      "data_source": "无",
      "holdings": [],
      "success": true
    },
    {
      "code": "004856",
      "name": "广发中证全指原材料ETF联接A",
      "estimation": 0.32,
      "net_value": 0.9493,
      "est_value": 0.9523,
      "update_time": "2026-04-07 11:30",
      "data_source": "天天基金实时",
      "holdings": [],
      "success": true
    },
    {
      "code": "007937",
      "name": "华夏中证新能源ETF联接A",
      "estimation": 0.0,
      "net_value": null,
      "est_value": null,
      "update_time": "无数据",
      "data_source": "无",
      "holdings": [],
      "success": true
    },
    {
      "code": "159876",
      "name": "博时有色金属ETF",
      "estimation": 0.07,
      "net_value": 1.0204,
      "est_value": 1.0211,
      "update_time": "2026-04-07 11:30",
      "data_source": "天天基金实时",
      "holdings": [],
      "success": true
    },
    {
      "code": "515700",
      "name": "国泰中证钢铁ETF",
      "estimation": -0.54,
      "net_value": 2.3983,
      "est_value": 2.3853,
      "update_time": "2026-04-07 11:30",
      "data_source": "天天基金实时",
      "holdings": [],
      "success": true
    },
    {
      "code": "516780",
      "name": "华宝中证有色金属ETF",
      "estimation": 0.56,
      "net_value": 1.7482,
      "est_value": 1.758,
      "update_time": "2026-04-07 11:30",
      "data_source": "天天基金实时",
      "holdings": [],
      "success": true
    },
    {
      "code": "516850",
      "name": "华夏中证新能源ETF",
      "estimation": -0.27,
      "net_value": 1.0478,
      "est_value": 1.045,
      "update_time": "2026-04-07 11:30",
      "data_source": "天天基金实时",
      "holdings": [],
      "success": true
    },
    {
      "code": "159755",
      "name": "国泰中证钢铁ETF",
      "estimation": -0.35,
      "net_value": 1.0451,
      "est_value": 1.0414,
      "update_time": "2026-04-07 11:30",
      "data_source": "天天基金实时",
      "holdings": [],
      "success": true
    },
    {
      "code": "000217",
      "name": "华安黄金易ETF联接A",
      "estimation": -0.34,
      "net_value": 3.4941,
      "est_value": 3.4822,
      "update_time": "2026-04-07 11:53",
      "data_source": "天天基金实时",
      "holdings": [],
      "success": true
    },
    {
      "code": "518880",
      "name": "华安黄金易ETF",
      "estimation": -0.34,
      "net_value": 9.8674,
      "est_value": 9.8338,
      "update_time": "2026-04-07 11:53",
      "data_source": "天天基金实时",
      "holdings": [],
      "success": true
    },
    {
      "code": "518800",
      "name": "国泰黄金ETF",
      "estimation": -0.35,
      "net_value": 9.7481,
      "est_value": 9.714,
      "update_time": "2026-04-07 11:55",
      "data_source": "天天基金实时",
      "holdings": [],
      "success": true
    },
    {
      "code": "159937",
      "name": "博时黄金ETF",
      "estimation": -0.34,
      "net_value": 9.8443,
      "est_value": 9.8108,
      "update_time": "2026-04-07 11:53",
      "data_source": "天天基金实时",
      "holdings": [],
      "success": true
    },
    {
      "code": "159934",
      "name": "易方达黄金ETF",
      "estimation": -0.35,
      "net_value": 10.3086,
      "est_value": 10.2725,
      "update_time": "2026-04-07 11:55",
      "data_source": "天天基金实时",
      "holdings": [],
      "success": true
    },
    {
      "code": "004253",
      "name": "国泰黄金ETF联接A",
      "estimation": -0.34,
      "net_value": 3.6604,
      "est_value": 3.6479,
      "update_time": "2026-04-07 11:53",
      "data_source": "天天基金实时",
      "holdings": [],
      "success": true
    },
    {
      "code": "002610",
      "name": "博时黄金ETF联接A",
      "estimation": -0.35,
      "net_value": 3.372,
      "est_value": 3.3602,
      "update_time": "2026-04-07 11:55",
      "data_source": "天天基金实时",
      "holdings": [],
      "success": true
    },
    {
      "code": "002611",
      "name": "博时黄金ETF联接C",
      "estimation": -0.34,
      "net_value": 3.2546,
      "est_value": 3.2435,
      "update_time": "2026-04-07 11:53",
      "data_source": "天天基金实时",
      "holdings": [],
      "success": true
    },
    {
      "code": "004254",
      "name": "国泰黄金ETF联接C",
      "estimation": 0.0,
      "net_value": null,
      "est_value": null,
      "update_time": "无数据",
      "data_source": "无",
      "holdings": [],
      "success": true
    },
    {
      "code": "159812",
      "name": "易方达黄金ETF",
      "estimation": -0.35,
      "net_value": 9.8289,
      "est_value": 9.7945,
      "update_time": "2026-04-07 11:55",
      "data_source": "天天基金实时",
      "holdings": [],
      "success": true
    },
    {
      "code": "004046",
      "name": "华安纳斯达克100(QDII)",
      "estimation": 0.0,
      "net_value": null,
      "est_value": null,
      "update_time": "无数据",
      "data_source": "无",
      "holdings": [],
      "success": true
    },
    {
      "code": "040046",
      "name": "华安纳斯达克100指数(QDII)",
      "estimation": 0.58,
      "net_value": 6.8363,
      "est_value": 6.8759,
      "update_time": "2026-04-07 04:00",
      "data_source": "天天基金实时",
      "holdings": [],
      "success": true
    },
    {
      "code": "161125",
      "name": "易方达标普500指数(QDII-LOF)A",
      "estimation": 0.28,
      "net_value": 2.7648,
      "est_value": 2.7725,
      "update_time": "2026-04-07 04:00",
      "data_source": "天天基金实时",
      "holdings": [],
      "success": true
    },
    {
      "code": "270042",
      "name": "广发纳斯达克100指数A(QDII)",
      "estimation": 0.58,
      "net_value": 6.8214,
      "est_value": 6.8609,
      "update_time": "2026-04-07 04:00",
      "data_source": "天天基金实时",
      "holdings": [],
      "success": true
    },
    {
      "code": "164906",
      "name": "交银中证海外中国互联网指数(QDII-LOF)",
      "estimation": 0.0,
      "net_value": null,
      "est_value": null,
      "update_time": "无数据",
      "data_source": "无",
      "holdings": [],
      "success": true
    },
    {
      "code": "000055",
      "name": "广发纳斯达克100指数A(QDII)",
      "estimation": 0.58,
      "net_value": 0.9903,
      "est_value": 0.996,
      "update_time": "2026-04-07 04:00",
      "data_source": "天天基金实时",
      "holdings": [],
      "success": true
    },
    {
      "code": "000369",
      "name": "广发全球医疗保健(QDII)",
      "estimation": 0.21,
      "net_value": 2.409,
      "est_value": 2.4141,
      "update_time": "2026-04-07 04:00",
      "data_source": "天天基金实时",
      "holdings": [],
      "success": true
    },
    {
      "code": "001668",
      "name": "汇添富全球互联混合(QDII)",
      "estimation": 0.29,
      "net_value": 4.2547,
      "est_value": 4.2671,
      "update_time": "2026-04-07 04:00",
      "data_source": "天天基金实时",
      "holdings": [],
      "success": true
    },
    {
      "code": "002423",
      "name": "华宝香港中小A(QDII-LOF)",
      "estimation": 0.31,
      "net_value": 0.3943,
      "est_value": 0.3955,
      "update_time": "2026-04-07 04:00",
      "data_source": "天天基金实时",
      "holdings": [],
      "success": true
    },
    {
      "code": "003385",
      "name": "工银全球美元债A(QDII)",
      "estimation": 0.0,
      "net_value": null,
      "est_value": null,
      "update_time": "无数据",
      "data_source": "无",
      "holdings": [],
      "success": true
    },
    {
      "code": "005534",
      "name": "长信美国标普100等权指数(QDII)",
      "estimation": 0.0,
      "net_value": null,
      "est_value": null,
      "update_time": "无数据",
      "data_source": "无",
      "holdings": [],
      "success": true
    },
    {
      "code": "006479",
      "name": "广发纳斯达克生物科技指数(QDII)",
      "estimation": 0.58,
      "net_value": 6.7068,
      "est_value": 6.7457,
      "update_time": "2026-04-07 04:00",
      "data_source": "天天基金实时",
      "holdings": [],
      "success": true
    },
    {
      "code": "007844",
      "name": "华夏恒生互联网科技业ETF(QDII)联接A",
      "estimation": 0.31,
      "net_value": 0.9263,
      "est_value": 0.9292,
      "update_time": "2026-04-07 04:00",
      "data_source": "天天基金实时",
      "holdings": [],
      "success": true
    },
    {
      "code": "008975",
      "name": "嘉实全球互联网股票(QDII)",
      "estimation": -0.27,
      "net_value": 1.1924,
      "est_value": 1.1892,
      "update_time": "2026-04-07 11:30",
      "data_source": "天天基金实时",
      "holdings": [],
      "success": true
    },
    {
      "code": "010393",
      "name": "易方达标普信息科技指数(QDII-LOF)A",
      "estimation": -0.26,
      "net_value": 0.867,
      "est_value": 0.8647,
      "update_time": "2026-04-07 11:30",
      "data_source": "天天基金实时",
      "holdings": [],
      "success": true
    },
    {
      "code": "011612",
      "name": "易方达中证海外中国互联网50ETF联接C",
      "estimation": 1.63,
      "net_value": 1.0086,
      "est_value": 1.025,
      "update_time": "2026-04-07 11:30",
      "data_source": "天天基金实时",
      "holdings": [],
      "success": true
    },
    {
      "code": "012868",
      "name": "华夏恒生科技ETF(QDII)联接A",
      "estimation": 0.29,
      "net_value": 5.2006,
      "est_value": 5.2156,
      "update_time": "2026-04-07 04:00",
      "data_source": "天天基金实时",
      "holdings": [],
      "success": true
    },
    {
      "code": "013055",
      "name": "易方达纳斯达克100ETF联接(QDII)A",
      "estimation": 0.0,
      "net_value": null,
      "est_value": null,
      "update_time": "无数据",
      "data_source": "无",
      "holdings": [],
      "success": true
    },
    {
      "code": "159605",
      "name": "易方达中证海外中国互联网50ETF",
      "estimation": 0.0,
      "net_value": null,
      "est_value": null,
      "update_time": "无数据",
      "data_source": "无",
      "holdings": [],
      "success": true
    },
    {
      "code": "513100",
      "name": "国泰纳斯达克100ETF",
      "estimation": 0.58,
      "net_value": 1.6551,
      "est_value": 1.6647,
      "update_time": "2026-04-07 04:00",
      "data_source": "天天基金实时",
      "holdings": [],
      "success": true
    },
    {
      "code": "513330",
      "name": "华夏恒生科技ETF(QDII)",
      "estimation": -2.02,
      "net_value": 0.4137,
      "est_value": 0.4053,
      "update_time": "2026-04-02 16:00",
      "data_source": "天天基金实时",
      "holdings": [],
      "success": true
    },
    {
      "code": "513880",
      "name": "华夏恒生互联网科技业ETF(QDII)",
      "estimation": 0.0,
      "net_value": null,
      "est_value": null,
      "update_time": "无数据",
      "data_source": "无",
      "holdings": [],
      "success": true
    },
    {
      "code": "159941",
      "name": "广发纳斯达克100ETF",
      "estimation": 0.58,
      "net_value": 1.2432,
      "est_value": 1.2504,
      "update_time": "2026-04-07 04:00",
      "data_source": "天天基金实时",
      "holdings": [],
      "success": true
    },
    {
      "code": "513500",
      "name": "博时标普500ETF(QDII)",
      "estimation": 0.32,
      "net_value": 2.1417,
      "est_value": 2.1485,
      "update_time": "2026-04-07 04:00",
      "data_source": "天天基金实时",
      "holdings": [],
      "success": true
    },
    {
      "code": "513520",
      "name": "华夏恒生ETF(QDII)",
      "estimation": 0.0,
      "net_value": null,
      "est_value": null,
      "update_time": "无数据",
      "data_source": "无",
      "holdings": [],
      "success": true
    }
  ]
}